simple_etl/__init__.py
data_integration_and_transformation_library-0.0.0.dist-info/METADATA
data_integration_and_transformation_library-0.0.0.dist-info/WHEEL
data_integration_and_transformation_library-0.0.0.dist-info/top_level.txt
data_integration_and_transformation_library-0.0.0.dist-info/RECORD
