Metadata-Version: 2.1
Name: data-integration-and-transformation-library
Version: 0.0.0
Summary: Coming soon
Author-email: Jochen Gietzen <jochen.gietzen@gmail.com>
